geoutils/LandsatGLAD.py
geoutils/__init__.py
geoutils/cube.py
geoutils/dataClean.py
geoutils/dataExtraction.py
geoutils/grid.py
geoutils/image.py
geoutils/modeling.py
geoutils/modisAPI.py
geoutils/utils.py
pochas_geoutils-1.0.1.dist-info/LICENSE
pochas_geoutils-1.0.1.dist-info/METADATA
pochas_geoutils-1.0.1.dist-info/WHEEL
pochas_geoutils-1.0.1.dist-info/entry_points.txt
pochas_geoutils-1.0.1.dist-info/top_level.txt
pochas_geoutils-1.0.1.dist-info/RECORD
