Metadata-Version: 2.1
Name: pochas-geoutils
Version: 1.0.1
Summary: A Python package includes geo-utils for PoCHAS project
Home-page: https://github.com/behzad89/pochas-geoutils
Author: Behzad Valipour Sh.
Author-email: behzad.valipour@swisstph.ch
License: MIT
Classifier: License :: OSI Approved :: MIT License
Classifier: Operating System :: OS Independent
Classifier: Programming Language :: Python :: 3
Classifier: Programming Language :: Python :: 3.7
License-File: LICENSE
Requires-Dist: numpy
Requires-Dist: geopandas
Requires-Dist: shapely
Requires-Dist: pandas
Requires-Dist: xarray
Requires-Dist: rioxarray
Requires-Dist: rasterio
Requires-Dist: netcdf4
Requires-Dist: requests
Requires-Dist: sklearn
Requires-Dist: xlsxwriter
Requires-Dist: coloredlogs
